README.txt
setup.py
collective/__init__.py
collective.namedblobfile.egg-info/PKG-INFO
collective.namedblobfile.egg-info/SOURCES.txt
collective.namedblobfile.egg-info/dependency_links.txt
collective.namedblobfile.egg-info/namespace_packages.txt
collective.namedblobfile.egg-info/not-zip-safe
collective.namedblobfile.egg-info/requires.txt
collective.namedblobfile.egg-info/top_level.txt
collective/namedblobfile/__init__.py
collective/namedblobfile/blobfile.py
collective/namedblobfile/blobimage.py
collective/namedblobfile/configure.zcml
collective/namedblobfile/field.py
collective/namedblobfile/interfaces.py
collective/namedblobfile/widget.py