Metadata-Version: 1.0
Name: collective.namedblobfile
Version: 0.3
Summary: File field and widget with enhancements for zope3 (using blobs for storage).
Home-page: http://svn.plone.org/svn/collective/collective.namedblobfile
Author: Dirceu Pereira Tiegs
Author-email: dirceutiegs@gmail.com
License: ZPL 2.1
Platform: UNKNOWN
Classifier: Framework :: Zope3
Classifier: Programming Language :: Python
Classifier: License :: OSI Approved :: Zope Public License
Classifier: Operating System :: OS Independent
Classifier: Topic :: Internet :: WWW/HTTP :: Dynamic Content
Classifier: Topic :: Software Development :: Libraries :: Python Modules
